shodan_data_ships/__init__.py
shodan_data_ships/client.py
shodan_data_ships/model.py
shodan_data_ships-0.1.2.dist-info/WHEEL
shodan_data_ships-0.1.2.dist-info/METADATA
shodan_data_ships-0.1.2.dist-info/RECORD
