Metadata-Version: 2.1
Name: shodan-data-ships
Version: 0.1.2
Summary: Library for consuming data from the Open Ships data feed from Shodan
Author: John Matherly
Author-email: jmath@shodan.io
Requires-Python: >=3.6.1,<4.0.0
Classifier: Programming Language :: Python :: 3
Classifier: Programming Language :: Python :: 3.7
Classifier: Programming Language :: Python :: 3.8
Classifier: Programming Language :: Python :: 3.9
Requires-Dist: httpx[brotli,http2] (>=0.19.0,<0.20.0)
Requires-Dist: pydantic (>=1.8.2,<2.0.0)
